SakharnyiMLToolkit/__init__.py
SakharnyiMLToolkit/FeatureExt/FeatureExtraction.py
SakharnyiMLToolkit/FeatureExt/__init__.py
SakharnyiMLToolkit/HyperOpt/HyperOpt.py
SakharnyiMLToolkit/HyperOpt/__init__.py
SakharnyiMLToolkit/Validation/Validation.py
SakharnyiMLToolkit/Validation/__init__.py
SakharnyiMLToolkit-0.29.dist-info/METADATA
SakharnyiMLToolkit-0.29.dist-info/WHEEL
SakharnyiMLToolkit-0.29.dist-info/top_level.txt
SakharnyiMLToolkit-0.29.dist-info/RECORD
